pyspel/__init__.py
pyspel/pyspel.py
pyspel-1.0.2.dist-info/LICENSE
pyspel-1.0.2.dist-info/METADATA
pyspel-1.0.2.dist-info/WHEEL
pyspel-1.0.2.dist-info/top_level.txt
pyspel-1.0.2.dist-info/RECORD
